cutie.py
cutie-0.3.2.dist-info/METADATA
cutie-0.3.2.dist-info/WHEEL
cutie-0.3.2.dist-info/top_level.txt
cutie-0.3.2.dist-info/RECORD
