Metadata-Version: 2.1
Name: cutie
Version: 0.3.2
Summary: Commandline User Tools for Input Easification
Home-page: https://github.com/kamik423/cutie
Author: Hans / Kamik423
Author-email: contact.kamik423@gmail.com
License: MIT
Classifier: Programming Language :: Python :: 3.6
Classifier: Programming Language :: Python :: 3.7
Classifier: Programming Language :: Python :: 3.8
Classifier: Programming Language :: Python :: 3.9
Classifier: Programming Language :: Python :: 3.10
Classifier: Programming Language :: Python :: 3 :: Only
Classifier: License :: OSI Approved :: MIT License
Classifier: Operating System :: OS Independent
Requires-Python: >=3.6
Requires-Dist: colorama
Requires-Dist: readchar (!=3.0.5)
